gpt_ask/__init__.py
gpt_ask-1.0.0.dist-info/METADATA
gpt_ask-1.0.0.dist-info/WHEEL
gpt_ask-1.0.0.dist-info/entry_points.txt
gpt_ask-1.0.0.dist-info/top_level.txt
gpt_ask-1.0.0.dist-info/RECORD
