Metadata-Version: 2.1
Name: gpt-ask
Version: 1.0.0
Summary: tui interactice chat gpt
Author: Eric Régnier
Author-email: utopman@gmail.com
Keywords: devtool
Classifier: Intended Audience :: Developers
Classifier: Programming Language :: Python :: 3
Classifier: Programming Language :: Python :: 3.8
Classifier: Programming Language :: Python :: 3.9
Classifier: Programming Language :: Python :: 3.10
Requires-Dist: openai
Requires-Dist: pygments
